[
  {
    "path": "posts/article5/",
    "title": "Article 5",
    "description": "Physics of snakeskin sheds light on sidewinding",
    "author": [
      {
        "name": "Shawn Lemaire",
        "url": {
          "https://github.com/ShawnLemaire": {}
        }
      }
    ],
    "date": "2021-02-28",
    "categories": [
      "English for Science"
    ],
    "preview": "posts/article5/photoserpent.png",
    "last_modified": "2021-02-28T11:58:01+01:00",
    "preview_width": 441,
    "preview_height": 441
  },
  {
    "path": "posts/article1/",
    "title": "Article 1",
    "description": "Discovery enables adult skin to regenerate like a newborn's",
    "author": [
      {
        "name": "Shawn Lemaire",
        "url": {
          "https://github.com/ShawnLemaire": {}
        }
      }
    ],
    "date": "2020-12-07",
    "categories": [
      "English for Science"
    ],
    "preview": "posts/article1/Imagearticle1.png",
    "last_modified": "2020-12-07T21:16:51+01:00",
    "preview_width": 360,
    "preview_height": 360
  },
  {
    "path": "posts/article2/",
    "title": "Article 2",
    "description": "Green is more than skin-deep for hundreds of frog species",
    "author": [
      {
        "name": "Shawn Lemaire",
        "url": {
          "https://github.com/ShawnLemaire": {}
        }
      }
    ],
    "date": "2020-12-07",
    "categories": [
      "English for Science"
    ],
    "preview": "posts/article2/Imagearticle2.png",
    "last_modified": "2020-12-07T21:29:55+01:00",
    "preview_width": 256,
    "preview_height": 256
  },
  {
    "path": "posts/article3/",
    "title": "Article 3",
    "description": "How Ultra-Black Fish Disappear in the Deepest Seas",
    "author": [
      {
        "name": "Shawn Lemaire",
        "url": {
          "https://github.com/ShawnLemaire": {}
        }
      }
    ],
    "date": "2020-12-07",
    "categories": [
      "English for Science"
    ],
    "preview": "posts/article3/Imagearticle3.png",
    "last_modified": "2020-12-07T21:19:50+01:00",
    "preview_width": 369,
    "preview_height": 369
  },
  {
    "path": "posts/article4/",
    "title": "Article 4",
    "description": "Snakes reveal the origin of skin colours",
    "author": [
      {
        "name": "Shawn Lemaire",
        "url": {
          "https://github.com/ShawnLemaire": {}
        }
      }
    ],
    "date": "2020-12-07",
    "categories": [
      "English for Science"
    ],
    "preview": "posts/article4/Imagearticle4.png",
    "last_modified": "2020-12-07T21:20:49+01:00",
    "preview_width": 500,
    "preview_height": 500
  },
  {
    "path": "posts/meal/",
    "title": "My English Activity Log : MEAL",
    "description": {},
    "author": [
      {
        "name": "Shawn Lemaire",
        "url": {}
      }
    ],
    "date": "2020-12-07",
    "categories": [
      "English for Science",
      "M.E.A.L."
    ],
    "preview": {},
    "last_modified": "2020-12-07T13:00:30+01:00"
  },
  {
    "path": "posts/2019-10-24-bacteria-antobiotics/",
    "title": "Bacterium adaptation",
    "description": "Analysis of \"More than 6,000 antibiotic resistance genes discovered in the bacteria that inhabit the human gut\"",
    "author": [
      {
        "name": "Student Unknown",
        "url": {}
      },
      {
        "name": "Nicolas Devilez",
        "url": {}
      },
      {
        "name": "Engels Guyliann",
        "url": "https://guyliann.netlify.com/fr"
      }
    ],
    "date": "2020-11-15",
    "categories": [
      "English for Science"
    ],
    "preview": {},
    "last_modified": "2020-11-15T18:21:23+01:00"
  },
  {
    "path": "posts/2020-11-15-graphicdescription/",
    "title": "Graphic description",
    "description": "This article deals with data on Zooplankton",
    "author": [
      {
        "name": "Shawn Lemaire",
        "url": {
          "https://github.com/ShawnLemaire": {}
        }
      }
    ],
    "date": "2020-11-15",
    "categories": [
      "Data Sciences I"
    ],
    "preview": "posts/2020-11-15-graphicdescription/graphicdescription_files/figure-html5/unnamed-chunk-2-1.png",
    "last_modified": "2020-11-15T16:35:42+01:00",
    "preview_width": 1248,
    "preview_height": 768
  },
  {
    "path": "posts/about/",
    "title": "About Me",
    "description": "This way to know who I am and why I'm here !",
    "author": [
      {
        "name": "Shawn Lemaire",
        "url": {}
      }
    ],
    "date": "2020-11-15",
    "categories": [],
    "preview": {},
    "last_modified": "2020-11-15T17:37:24+01:00"
  }
]
